gherkbot/__init__.py
gherkbot/cli.py
gherkbot/converter.py
gherkbot/parser.py
gherkbot/strategies.py
gherkbot/synchronizer.py
gherkbot-0.1.5.dist-info/METADATA
gherkbot-0.1.5.dist-info/WHEEL
gherkbot-0.1.5.dist-info/entry_points.txt
gherkbot-0.1.5.dist-info/RECORD
