Metadata-Version: 2.4
Name: gherkbot
Version: 0.1.5
Summary: A tool to convert Gherkin feature files to Robot Framework format.
Project-URL: Homepage, https://github.com/schlich/gherkbot
Project-URL: Documentation, https://github.com/schlich/gherkbot#readme
Project-URL: Issues, https://github.com/schlich/gherkbot/issues
Project-URL: Repository, https://github.com/schlich/gherkbot
Author-email: schlich <ty.schlich@gmail.com>
Classifier: Development Status :: 4 - Beta
Classifier: Environment :: Console
Classifier: Framework :: Robot Framework
Classifier: Intended Audience :: Developers
Classifier: License :: OSI Approved :: MIT License
Classifier: Operating System :: OS Independent
Classifier: Programming Language :: Python :: 3
Classifier: Programming Language :: Python :: 3.12
Classifier: Topic :: Software Development :: Code Generators
Classifier: Topic :: Software Development :: Testing
Classifier: Topic :: Utilities
Requires-Python: >=3.12
Requires-Dist: gherkin-official>=32.1.2
Requires-Dist: pydantic>=2.11.5
Requires-Dist: robotframework>=7.3
Requires-Dist: typer>=0.16.0
